expyro/__init__.py
expyro/_artifacts.py
expyro/_cli.py
expyro/_experiment.py
expyro/_hook.py
expyro/_postprocessing.py
expyro/py.typed
expyro-0.0.8.dist-info/licenses/LICENSE
expyro-0.0.8.dist-info/METADATA
expyro-0.0.8.dist-info/WHEEL
expyro-0.0.8.dist-info/entry_points.txt
expyro-0.0.8.dist-info/top_level.txt
expyro-0.0.8.dist-info/RECORD
