Metadata-Version: 2.4
Name: expyro
Version: 0.0.8
Summary: A lightweight library to manage reproducible experiments.
Author: Lukas Haverbeck
License: MIT License
Project-URL: Homepage, https://github.com/lukashaverbeck/expyro
Project-URL: Issues, https://github.com/lukashaverbeck/expyro/issues
Keywords: experiment-tracking,reproducibility
Classifier: Programming Language :: Python :: 3
Classifier: Programming Language :: Python :: 3.12
Classifier: Programming Language :: Python :: 3.13
Classifier: License :: OSI Approved :: MIT License
Classifier: Operating System :: OS Independent
Classifier: Typing :: Typed
Requires-Python: >=3.12
License-File: LICENSE
Requires-Dist: tyro>=0.9.28
Provides-Extra: dev
Requires-Dist: build>=1.2; extra == "dev"
Requires-Dist: twine>=5; extra == "dev"
Requires-Dist: pandas-stubs; extra == "dev"
Provides-Extra: matplotlib
Requires-Dist: matplotlib; extra == "matplotlib"
Provides-Extra: pandas
Requires-Dist: pandas; extra == "pandas"
Provides-Extra: all
Requires-Dist: matplotlib; extra == "all"
Requires-Dist: pandas; extra == "all"
Dynamic: license-file
